MANIFEST.in
README.md
requirements.txt
setup.py
untt/__init__.py
untt/entity.py
untt/ex.py
untt/field.py
untt/types.py
untt/util.py
untt.egg-info/PKG-INFO
untt.egg-info/SOURCES.txt
untt.egg-info/dependency_links.txt
untt.egg-info/requires.txt
untt.egg-info/top_level.txt