Metadata-Version: 1.1
Name: untt
Version: 0.1.1
Summary: Right, it's uEntity.
Home-page: http://untt.n9co.de
Author: Bagrat Aznauryan
Author-email: bagrat@aznauryan.org
License: MIT
Keywords: model orm entity untt
Platform: UNKNOWN
Classifier: Development Status :: 3 - Alpha
Classifier: Intended Audience :: Developers
Classifier: Intended Audience :: Information Technology
Classifier: License :: OSI Approved :: MIT License
Classifier: Programming Language :: Python :: 3.5
Classifier: Programming Language :: Python :: 3
Classifier: Programming Language :: Python :: 3 :: Only
Classifier: Topic :: Software Development
Classifier: Topic :: Software Development :: Libraries
Classifier: Topic :: Software Development :: Libraries :: Application Frameworks
